{
    "metadata": {
        "dataVersion": "2",
        "matchId": "KR_5549277357",
        "participants": [
            "tTO0g2IRRYQ8FZ8wrAmwjHXvJ_1YP3rheewDY2RxpWLW_0y3D4foavR8MpbVLiJcH7VbeuKuMHaEOA",
            "RbnzzaOX0GxrBG4BO0Dyg4WKd0wABU3PtmYu3vk-AVkN243aP7nMzAA4q_mhzenEMJcEYyOUi1JduQ",
            "3_WwIiXJ2TDomWsRoCXLzBOZmBVSVAN3AizDueTtx3q_vqs63SPI153XXXAHb1-iEwXOGWhadZAu1A",
            "Cpnel8WVmFF48qZEgoJFtpI4nUIHG-Pxg5ZbIQb1JGKLYcuWXD11gL0PTAoKTobUeXTVG2WnnfexBQ",
            "FvirJA67-7x3HItM14tHJEjp_pBUYBdqYqIuNTsDOOdBUJ_lhvGL-bIGLNwhmXdW5bWTNvHzZ4fDmw",
            "fyuLWfD6mhU-YkyofQnIq8b35lm1pH6ED6dH5eG-iZw2CMhoADTS14X-klLlGHO8A1hWaNxkNi6F8A",
            "6RDwd3gpnYlJY_wT3qHBNhX0wh4x3RLcW8xlCkIkZVTnlVZ1zXjACOaw4MGo2yPpZTF-vBuhGcLK0g",
            "nhrRyvO26pQB8ruZrvlp0JU5qW540H_diUDW_jFdPCqmquRjRncp6J1k1B1WAm-EtbM_UrdShkdUWw",
            "S0u2kZkfMqtiXGKZHZNwjv4937xWG99SD3P04AjGUBjuqI5uLdU4G2Po4de-bkHjs79xURXwnI7I3Q",
            "5K7-MVC9dFEiJ5cAYyf198ZWnnk0Uz4dPNdHdFFZV9jhvLLgFYP9UtIoZt-MsSqNCI32v70W2VPiag"
        ]
    },
    "info": {
        "gameCreation": 1636167634000,
        "gameDuration": 1723,
        "gameEndTimestamp": 1636169397217,
        "gameId": 5549277357,
        "gameMode": "CLASSIC",
        "gameName": "teambuilder-match-5549277357",
        "gameStartTimestamp": 1636167674147,
        "gameType": "MATCHED_GAME",
        "gameVersion": "11.22.406.3587",
        "mapId": 11,
        "participants": [
            {
                "assists": 8,
                "baronKills": 0,
                "bountyLevel": 0,
                "champExperience": 14155,
                "champLevel": 15,
                "championId": 104,
                "championName": "Graves",
                "championTransform": 0,
                "consumablesPurchased": 1,
                "damageDealtToBuildings": 470,
                "damageDealtToObjectives": 652,
                "damageDealtToTurrets": 470,
                "damageSelfMitigated": 22018,
                "deaths": 12,
                "detectorWardsPlaced": 0,
                "doubleKills": 0,
                "dragonKills": 0,
                "firstBloodAssist": false,
                "firstBloodKill": false,
                "firstTowerAssist": false,
                "firstTowerKill": false,
                "gameEndedInEarlySurrender": false,
                "gameEndedInSurrender": false,
                "goldEarned": 11606,
                "goldSpent": 11100,
                "individualPosition": "TOP",
                "inhibitorKills": 0,
                "inhibitorTakedowns": 0,
                "inhibitorsLost": 3,
                "item0": 3047,
                "item1": 6673,
                "item2": 6676,
                "item3": 3072,
                "item4": 0,
                "item5": 0,
                "item6": 3340,
                "itemsPurchased": 18,
                "killingSprees": 1,
                "kills": 5,
                "lane": "TOP",
                "largestCriticalStrike": 382,
                "largestKillingSpree": 2,
                "largestMultiKill": 1,
                "longestTimeSpentLiving": 304,
                "magicDamageDealt": 1368,
                "magicDamageDealtToChampions": 930,
                "magicDamageTaken": 4095,
                "neutralMinionsKilled": 5,
                "nexusKills": 0,
                "nexusLost": 1,
                "nexusTakedowns": 0,
                "objectivesStolen": 0,
                "objectivesStolenAssists": 0,
                "participantId": 1,
                "pentaKills": 0,
                "perks": {
                    "statPerks": {
                        "defense": 5002,
                        "flex": 5008,
                        "offense": 5005
                    },
                    "styles": [
                        {
                            "description": "primaryStyle",
                            "selections": [
                                {
                                    "perk": 8021,
                                    "var1": 2420,
                                    "var2": 1778,
                                    "var3": 0
                                },
                                {
                                    "perk": 8009,
                                    "var1": 1927,
                                    "var2": 0,
                                    "var3": 0
                                },
                                {
                                    "perk": 9104,
                                    "var1": 19,
                                    "var2": 40,
                                    "var3": 0
                                },
                                {
                                    "perk": 8014,
                                    "var1": 412,
                                    "var2": 0,
                                    "var3": 0
                                }
                            ],
                            "style": 8000
                        },
                        {
                            "description": "subStyle",
                            "selections": [
                                {
                                    "perk": 8304,
                                    "var1": 11,
                                    "var2": 1,
                                    "var3": 5
                                },
                                {
                                    "perk": 8345,
                                    "var1": 3,
                                    "var2": 0,
                                    "var3": 0
                                }
                            ],
                            "style": 8300
                        }
                    ]
                },
                "physicalDamageDealt": 139582,
                "physicalDamageDealtToChampions": 19344,
                "physicalDamageTaken": 20470,
                "profileIcon": 5030,
                "puuid": "tTO0g2IRRYQ8FZ8wrAmwjHXvJ_1YP3rheewDY2RxpWLW_0y3D4foavR8MpbVLiJcH7VbeuKuMHaEOA",
                "quadraKills": 0,
                "riotIdName": "",
                "riotIdTagline": "",
                "role": "SOLO",
                "sightWardsBoughtInGame": 0,
                "spell1Casts": 54,
                "spell2Casts": 30,
                "spell3Casts": 23,
                "spell4Casts": 10,
                "summoner1Casts": 3,
                "summoner1Id": 12,
                "summoner2Casts": 5,
                "summoner2Id": 4,
                "summonerId": "vDtuEhMbkiMGg_DCvgtZp5IZ3-HFGJ6i-Wl9miiiZYf-T9ojKE8f609ALQ",
                "summonerLevel": 72,
                "summonerName": "정글골통분해기",
                "teamEarlySurrendered": false,
                "teamId": 100,
                "teamPosition": "TOP",
                "timeCCingOthers": 15,
                "timePlayed": 1723,
                "totalDamageDealt": 143703,
                "totalDamageDealtToChampions": 20421,
                "totalDamageShieldedOnTeammates": 0,
                "totalDamageTaken": 27964,
                "totalHeal": 2396,
                "totalHealsOnTeammates": 0,
                "totalMinionsKilled": 177,
                "totalTimeCCDealt": 242,
                "totalTimeSpentDead": 279,
                "totalUnitsHealed": 1,
                "tripleKills": 0,
                "trueDamageDealt": 2751,
                "trueDamageDealtToChampions": 146,
                "trueDamageTaken": 3399,
                "turretKills": 0,
                "turretTakedowns": 0,
                "turretsLost": 10,
                "unrealKills": 0,
                "visionScore": 12,
                "visionWardsBoughtInGame": 0,
                "wardsKilled": 2,
                "wardsPlaced": 6,
                "win": false
            },
            {
                "assists": 4,
                "baronKills": 0,
                "bountyLevel": 0,
                "champExperience": 15103,
                "champLevel": 16,
                "championId": 64,
                "championName": "LeeSin",
                "championTransform": 0,
                "consumablesPurchased": 16,
                "damageDealtToBuildings": 3040,
                "damageDealtToObjectives": 14323,
                "damageDealtToTurrets": 3040,
                "damageSelfMitigated": 22419,
                "deaths": 9,
                "detectorWardsPlaced": 14,
                "doubleKills": 1,
                "dragonKills": 1,
                "firstBloodAssist": false,
                "firstBloodKill": false,
                "firstTowerAssist": false,
                "firstTowerKill": false,
                "gameEndedInEarlySurrender": false,
                "gameEndedInSurrender": false,
                "goldEarned": 14865,
                "goldSpent": 12450,
                "individualPosition": "JUNGLE",
                "inhibitorKills": 0,
                "inhibitorTakedowns": 0,
                "inhibitorsLost": 3,
                "item0": 2055,
                "item1": 3142,
                "item2": 6630,
                "item3": 3158,
                "item4": 3071,
                "item5": 3123,
                "item6": 3340,
                "itemsPurchased": 31,
                "killingSprees": 2,
                "kills": 11,
                "lane": "JUNGLE",
                "largestCriticalStrike": 0,
                "largestKillingSpree": 5,
                "largestMultiKill": 2,
                "longestTimeSpentLiving": 353,
                "magicDamageDealt": 47960,
                "magicDamageDealtToChampions": 3377,
                "magicDamageTaken": 8507,
                "neutralMinionsKilled": 100,
                "nexusKills": 0,
                "nexusLost": 1,
                "nexusTakedowns": 0,
                "objectivesStolen": 0,
                "objectivesStolenAssists": 0,
                "participantId": 2,
                "pentaKills": 0,
                "perks": {
                    "statPerks": {
                        "defense": 5002,
                        "flex": 5008,
                        "offense": 5005
                    },
                    "styles": [
                        {
                            "description": "primaryStyle",
                            "selections": [
                                {
                                    "perk": 8010,
                                    "var1": 311,
                                    "var2": 0,
                                    "var3": 0
                                },
                                {
                                    "perk": 9111,
                                    "var1": 912,
                                    "var2": 300,
                                    "var3": 0
                                },
                                {
                                    "perk": 9104,
                                    "var1": 13,
                                    "var2": 10,
                                    "var3": 0
                                },
                                {
                                    "perk": 8014,
                                    "var1": 518,
                                    "var2": 0,
                                    "var3": 0
                                }
                            ],
                            "style": 8000
                        },
                        {
                            "description": "subStyle",
                            "selections": [
                                {
                                    "perk": 8304,
                                    "var1": 9,
                                    "var2": 4,
                                    "var3": 5
                                },
                                {
                                    "perk": 8347,
                                    "var1": 0,
                                    "var2": 0,
                                    "var3": 0
                                }
                            ],
                            "style": 8300
                        }
                    ]
                },
                "physicalDamageDealt": 101969,
                "physicalDamageDealtToChampions": 16144,
                "physicalDamageTaken": 23464,
                "profileIcon": 3556,
                "puuid": "RbnzzaOX0GxrBG4BO0Dyg4WKd0wABU3PtmYu3vk-AVkN243aP7nMzAA4q_mhzenEMJcEYyOUi1JduQ",
                "quadraKills": 0,
                "riotIdName": "",
                "riotIdTagline": "",
                "role": "NONE",
                "sightWardsBoughtInGame": 0,
                "spell1Casts": 171,
                "spell2Casts": 135,
                "spell3Casts": 112,
                "spell4Casts": 10,
                "summoner1Casts": 19,
                "summoner1Id": 11,
                "summoner2Casts": 6,
                "summoner2Id": 4,
                "summonerId": "0AfH0f03rua3knmD14_S2WKIDPDq6YbcHt7mYYC3sCzKsg",
                "summonerLevel": 236,
                "summonerName": "IIlllIIllllIIIl",
                "teamEarlySurrendered": false,
                "teamId": 100,
                "teamPosition": "JUNGLE",
                "timeCCingOthers": 27,
                "timePlayed": 1723,
                "totalDamageDealt": 160007,
                "totalDamageDealtToChampions": 20851,
                "totalDamageShieldedOnTeammates": 382,
                "totalDamageTaken": 33798,
                "totalHeal": 6199,
                "totalHealsOnTeammates": 0,
                "totalMinionsKilled": 76,
                "totalTimeCCDealt": 462,
                "totalTimeSpentDead": 216,
                "totalUnitsHealed": 1,
                "tripleKills": 0,
                "trueDamageDealt": 10078,
                "trueDamageDealtToChampions": 1330,
                "trueDamageTaken": 1826,
                "turretKills": 1,
                "turretTakedowns": 1,
                "turretsLost": 10,
                "unrealKills": 0,
                "visionScore": 37,
                "visionWardsBoughtInGame": 16,
                "wardsKilled": 5,
                "wardsPlaced": 24,
                "win": false
            },
            {
                "assists": 7,
                "baronKills": 0,
                "bountyLevel": 0,
                "champExperience": 13913,
                "champLevel": 15,
                "championId": 4,
                "championName": "TwistedFate",
                "championTransform": 0,
                "consumablesPurchased": 2,
                "damageDealtToBuildings": 931,
                "damageDealtToObjectives": 931,
                "damageDealtToTurrets": 931,
                "damageSelfMitigated": 12015,
                "deaths": 9,
                "detectorWardsPlaced": 2,
                "doubleKills": 0,
                "dragonKills": 0,
                "firstBloodAssist": false,
                "firstBloodKill": false,
                "firstTowerAssist": false,
                "firstTowerKill": false,
                "gameEndedInEarlySurrender": false,
                "gameEndedInSurrender": false,
                "goldEarned": 10757,
                "goldSpent": 10800,
                "individualPosition": "MIDDLE",
                "inhibitorKills": 0,
                "inhibitorTakedowns": 0,
                "inhibitorsLost": 3,
                "item0": 3094,
                "item1": 3020,
                "item2": 6656,
                "item3": 0,
                "item4": 4628,
                "item5": 0,
                "item6": 3340,
                "itemsPurchased": 18,
                "killingSprees": 1,
                "kills": 4,
                "lane": "MIDDLE",
                "largestCriticalStrike": 87,
                "largestKillingSpree": 2,
                "largestMultiKill": 1,
                "longestTimeSpentLiving": 569,
                "magicDamageDealt": 110814,
                "magicDamageDealtToChampions": 20427,
                "magicDamageTaken": 4290,
                "neutralMinionsKilled": 0,
                "nexusKills": 0,
                "nexusLost": 1,
                "nexusTakedowns": 0,
                "objectivesStolen": 0,
                "objectivesStolenAssists": 0,
                "participantId": 3,
                "pentaKills": 0,
                "perks": {
                    "statPerks": {
                        "defense": 5003,
                        "flex": 5008,
                        "offense": 5005
                    },
                    "styles": [
                        {
                            "description": "primaryStyle",
                            "selections": [
                                {
                                    "perk": 8112,
                                    "var1": 1409,
                                    "var2": 0,
                                    "var3": 0
                                },
                                {
                                    "perk": 8139,
                                    "var1": 1257,
                                    "var2": 0,
                                    "var3": 0
                                },
                                {
                                    "perk": 8138,
                                    "var1": 30,
                                    "var2": 0,
                                    "var3": 0
                                },
                                {
                                    "perk": 8135,
                                    "var1": 1706,
                                    "var2": 5,
                                    "var3": 0
                                }
                            ],
                            "style": 8100
                        },
                        {
                            "description": "subStyle",
                            "selections": [
                                {
                                    "perk": 8316,
                                    "var1": 4462,
                                    "var2": 0,
                                    "var3": 0
                                },
                                {
                                    "perk": 8352,
                                    "var1": 296,
                                    "var2": 1299,
                                    "var3": 1012
                                }
                            ],
                            "style": 8300
                        }
                    ]
                },
                "physicalDamageDealt": 15468,
                "physicalDamageDealtToChampions": 2069,
                "physicalDamageTaken": 21177,
                "profileIcon": 3866,
                "puuid": "3_WwIiXJ2TDomWsRoCXLzBOZmBVSVAN3AizDueTtx3q_vqs63SPI153XXXAHb1-iEwXOGWhadZAu1A",
                "quadraKills": 0,
                "riotIdName": "",
                "riotIdTagline": "",
                "role": "SOLO",
                "sightWardsBoughtInGame": 0,
                "spell1Casts": 84,
                "spell2Casts": 138,
                "spell3Casts": 0,
                "spell4Casts": 13,
                "summoner1Casts": 4,
                "summoner1Id": 14,
                "summoner2Casts": 4,
                "summoner2Id": 4,
                "summonerId": "_KAM2ftEJoq3HebdbFFSuGwxq3uSCzK1WHM566OrIyRhtw",
                "summonerLevel": 328,
                "summonerName": "dopa71",
                "teamEarlySurrendered": false,
                "teamId": 100,
                "teamPosition": "MIDDLE",
                "timeCCingOthers": 42,
                "timePlayed": 1723,
                "totalDamageDealt": 130541,
                "totalDamageDealtToChampions": 23460,
                "totalDamageShieldedOnTeammates": 0,
                "totalDamageTaken": 27685,
                "totalHeal": 2792,
                "totalHealsOnTeammates": 0,
                "totalMinionsKilled": 191,
                "totalTimeCCDealt": 139,
                "totalTimeSpentDead": 311,
                "totalUnitsHealed": 1,
                "tripleKills": 0,
                "trueDamageDealt": 4257,
                "trueDamageDealtToChampions": 964,
                "trueDamageTaken": 2217,
                "turretKills": 0,
                "turretTakedowns": 0,
                "turretsLost": 10,
                "unrealKills": 0,
                "visionScore": 18,
                "visionWardsBoughtInGame": 2,
                "wardsKilled": 2,
                "wardsPlaced": 10,
                "win": false
            },
            {
                "assists": 7,
                "baronKills": 0,
                "bountyLevel": 0,
                "champExperience": 11722,
                "champLevel": 14,
                "championId": 236,
                "championName": "Lucian",
                "championTransform": 0,
                "consumablesPurchased": 4,
                "damageDealtToBuildings": 426,
                "damageDealtToObjectives": 1566,
                "damageDealtToTurrets": 426,
                "damageSelfMitigated": 9967,
                "deaths": 11,
                "detectorWardsPlaced": 0,
                "doubleKills": 0,
                "dragonKills": 0,
                "firstBloodAssist": false,
                "firstBloodKill": false,
                "firstTowerAssist": false,
                "firstTowerKill": false,
                "gameEndedInEarlySurrender": false,
                "gameEndedInSurrender": false,
                "goldEarned": 10445,
                "goldSpent": 10150,
                "individualPosition": "BOTTOM",
                "inhibitorKills": 0,
                "inhibitorTakedowns": 0,
                "inhibitorsLost": 3,
                "item0": 6671,
                "item1": 3033,
                "item2": 0,
                "item3": 3006,
                "item4": 3508,
                "item5": 0,
                "item6": 3363,
                "itemsPurchased": 25,
                "killingSprees": 1,
                "kills": 7,
                "lane": "BOTTOM",
                "largestCriticalStrike": 409,
                "largestKillingSpree": 2,
                "largestMultiKill": 1,
                "longestTimeSpentLiving": 258,
                "magicDamageDealt": 5251,
                "magicDamageDealtToChampions": 1795,
                "magicDamageTaken": 4183,
                "neutralMinionsKilled": 4,
                "nexusKills": 0,
                "nexusLost": 1,
                "nexusTakedowns": 0,
                "objectivesStolen": 0,
                "objectivesStolenAssists": 0,
                "participantId": 4,
                "pentaKills": 0,
                "perks": {
                    "statPerks": {
                        "defense": 5002,
                        "flex": 5008,
                        "offense": 5005
                    },
                    "styles": [
                        {
                            "description": "primaryStyle",
                            "selections": [
                                {
                                    "perk": 8005,
                                    "var1": 1589,
                                    "var2": 1034,
                                    "var3": 555
                                },
                                {
                                    "perk": 8009,
                                    "var1": 1465,
                                    "var2": 0,
                                    "var3": 0
                                },
                                {
                                    "perk": 9104,
                                    "var1": 19,
                                    "var2": 10,
                                    "var3": 0
                                },
                                {
                                    "perk": 8014,
                                    "var1": 311,
                                    "var2": 0,
                                    "var3": 0
                                }
                            ],
                            "style": 8000
                        },
                        {
                            "description": "subStyle",
                            "selections": [
                                {
                                    "perk": 8139,
                                    "var1": 924,
                                    "var2": 0,
                                    "var3": 0
                                },
                                {
                                    "perk": 8135,
                                    "var1": 1273,
                                    "var2": 4,
                                    "var3": 0
                                }
                            ],
                            "style": 8100
                        }
                    ]
                },
                "physicalDamageDealt": 95687,
                "physicalDamageDealtToChampions": 16183,
                "physicalDamageTaken": 15297,
                "profileIcon": 983,
                "puuid": "Cpnel8WVmFF48qZEgoJFtpI4nUIHG-Pxg5ZbIQb1JGKLYcuWXD11gL0PTAoKTobUeXTVG2WnnfexBQ",
                "quadraKills": 0,
                "riotIdName": "",
                "riotIdTagline": "",
                "role": "CARRY",
                "sightWardsBoughtInGame": 0,
                "spell1Casts": 57,
                "spell2Casts": 46,
                "spell3Casts": 45,
                "spell4Casts": 8,
                "summoner1Casts": 3,
                "summoner1Id": 4,
                "summoner2Casts": 5,
                "summoner2Id": 7,
                "summonerId": "9kFtlSG9nMXPQORHPAQ9NY-xrpYTJNaPAWMnhMM5uhBvmw",
                "summonerLevel": 153,
                "summonerName": "안양역 미친개",
                "teamEarlySurrendered": false,
                "teamId": 100,
                "teamPosition": "BOTTOM",
                "timeCCingOthers": 3,
                "timePlayed": 1723,
                "totalDamageDealt": 101938,
                "totalDamageDealtToChampions": 18293,
                "totalDamageShieldedOnTeammates": 0,
                "totalDamageTaken": 21113,
                "totalHeal": 2133,
                "totalHealsOnTeammates": 474,
                "totalMinionsKilled": 153,
                "totalTimeCCDealt": 43,
                "totalTimeSpentDead": 262,
                "totalUnitsHealed": 2,
                "tripleKills": 0,
                "trueDamageDealt": 1000,
                "trueDamageDealtToChampions": 314,
                "trueDamageTaken": 1632,
                "turretKills": 0,
                "turretTakedowns": 0,
                "turretsLost": 10,
                "unrealKills": 0,
                "visionScore": 13,
                "visionWardsBoughtInGame": 0,
                "wardsKilled": 3,
                "wardsPlaced": 8,
                "win": false
            },
            {
                "assists": 12,
                "baronKills": 0,
                "bountyLevel": 0,
                "champExperience": 10992,
                "champLevel": 13,
                "championId": 53,
                "championName": "Blitzcrank",
                "championTransform": 0,
                "consumablesPurchased": 6,
                "damageDealtToBuildings": 0,
                "damageDealtToObjectives": 290,
                "damageDealtToTurrets": 0,
                "damageSelfMitigated": 28988,
                "deaths": 12,
                "detectorWardsPlaced": 3,
                "doubleKills": 0,
                "dragonKills": 0,
                "firstBloodAssist": false,
                "firstBloodKill": false,
                "firstTowerAssist": false,
                "firstTowerKill": false,
                "gameEndedInEarlySurrender": false,
                "gameEndedInSurrender": false,
                "goldEarned": 7246,
                "goldSpent": 6975,
                "individualPosition": "UTILITY",
                "inhibitorKills": 0,
                "inhibitorTakedowns": 0,
                "inhibitorsLost": 3,
                "item0": 3857,
                "item1": 3190,
                "item2": 1029,
                "item3": 3050,
                "item4": 3117,
                "item5": 0,
                "item6": 3364,
                "itemsPurchased": 21,
                "killingSprees": 1,
                "kills": 3,
                "lane": "BOTTOM",
                "largestCriticalStrike": 0,
                "largestKillingSpree": 2,
                "largestMultiKill": 1,
                "longestTimeSpentLiving": 216,
                "magicDamageDealt": 11788,
                "magicDamageDealtToChampions": 6632,
                "magicDamageTaken": 7935,
                "neutralMinionsKilled": 0,
                "nexusKills": 0,
                "nexusLost": 1,
                "nexusTakedowns": 0,
                "objectivesStolen": 0,
                "objectivesStolenAssists": 0,
                "participantId": 5,
                "pentaKills": 0,
                "perks": {
                    "statPerks": {
                        "defense": 5001,
                        "flex": 5002,
                        "offense": 5007
                    },
                    "styles": [
                        {
                            "description": "primaryStyle",
                            "selections": [
                                {
                                    "perk": 8439,
                                    "var1": 405,
                                    "var2": 940,
                                    "var3": 0
                                },
                                {
                                    "perk": 8446,
                                    "var1": 0,
                                    "var2": 0,
                                    "var3": 0
                                },
                                {
                                    "perk": 8429,
                                    "var1": 58,
                                    "var2": 15,
                                    "var3": 13
                                },
                                {
                                    "perk": 8451,
                                    "var1": 193,
                                    "var2": 0,
                                    "var3": 0
                                }
                            ],
                            "style": 8400
                        },
                        {
                            "description": "subStyle",
                            "selections": [
                                {
                                    "perk": 8345,
                                    "var1": 3,
                                    "var2": 0,
                                    "var3": 0
                                },
                                {
                                    "perk": 8347,
                                    "var1": 0,
                                    "var2": 0,
                                    "var3": 0
                                }
                            ],
                            "style": 8300
                        }
                    ]
                },
                "physicalDamageDealt": 7008,
                "physicalDamageDealtToChampions": 3807,
                "physicalDamageTaken": 17298,
                "profileIcon": 5083,
                "puuid": "FvirJA67-7x3HItM14tHJEjp_pBUYBdqYqIuNTsDOOdBUJ_lhvGL-bIGLNwhmXdW5bWTNvHzZ4fDmw",
                "quadraKills": 0,
                "riotIdName": "",
                "riotIdTagline": "",
                "role": "SUPPORT",
                "sightWardsBoughtInGame": 0,
                "spell1Casts": 38,
                "spell2Casts": 34,
                "spell3Casts": 29,
                "spell4Casts": 15,
                "summoner1Casts": 9,
                "summoner1Id": 14,
                "summoner2Casts": 4,
                "summoner2Id": 4,
                "summonerId": "HpQgv8iWZUR70p7bqpX63i-WPGGDhUbLS1BNJ1uC4LVT1ko",
                "summonerLevel": 222,
                "summonerName": "2O2O JUG",
                "teamEarlySurrendered": false,
                "teamId": 100,
                "teamPosition": "UTILITY",
                "timeCCingOthers": 39,
                "timePlayed": 1723,
                "totalDamageDealt": 27479,
                "totalDamageDealtToChampions": 11670,
                "totalDamageShieldedOnTeammates": 305,
                "totalDamageTaken": 28013,
                "totalHeal": 0,
                "totalHealsOnTeammates": 0,
                "totalMinionsKilled": 27,
                "totalTimeCCDealt": 124,
                "totalTimeSpentDead": 291,
                "totalUnitsHealed": 0,
                "tripleKills": 0,
                "trueDamageDealt": 8682,
                "trueDamageDealtToChampions": 1230,
                "trueDamageTaken": 2779,
                "turretKills": 0,
                "turretTakedowns": 0,
                "turretsLost": 10,
                "unrealKills": 0,
                "visionScore": 39,
                "visionWardsBoughtInGame": 3,
                "wardsKilled": 3,
                "wardsPlaced": 18,
                "win": false
            },
            {
                "assists": 3,
                "baronKills": 0,
                "bountyLevel": 5,
                "champExperience": 19341,
                "champLevel": 18,
                "championId": 67,
                "championName": "Vayne",
                "championTransform": 0,
                "consumablesPurchased": 6,
                "damageDealtToBuildings": 12218,
                "damageDealtToObjectives": 19760,
                "damageDealtToTurrets": 12218,
                "damageSelfMitigated": 19638,
                "deaths": 6,
                "detectorWardsPlaced": 3,
                "doubleKills": 3,
                "dragonKills": 0,
                "firstBloodAssist": false,
                "firstBloodKill": true,
                "firstTowerAssist": false,
                "firstTowerKill": true,
                "gameEndedInEarlySurrender": false,
                "gameEndedInSurrender": false,
                "goldEarned": 18479,
                "goldSpent": 15300,
                "individualPosition": "TOP",
                "inhibitorKills": 0,
                "inhibitorTakedowns": 0,
                "inhibitorsLost": 0,
                "item0": 3139,
                "item1": 3006,
                "item2": 1038,
                "item3": 6673,
                "item4": 3046,
                "item5": 3124,
                "item6": 3363,
                "itemsPurchased": 31,
                "killingSprees": 6,
                "kills": 20,
                "lane": "TOP",
                "largestCriticalStrike": 435,
                "largestKillingSpree": 5,
                "largestMultiKill": 4,
                "longestTimeSpentLiving": 329,
                "magicDamageDealt": 793,
                "magicDamageDealtToChampions": 382,
                "magicDamageTaken": 5001,
                "neutralMinionsKilled": 27,
                "nexusKills": 0,
                "nexusLost": 0,
                "nexusTakedowns": 1,
                "objectivesStolen": 0,
                "objectivesStolenAssists": 0,
                "participantId": 6,
                "pentaKills": 0,
                "perks": {
                    "statPerks": {
                        "defense": 5002,
                        "flex": 5008,
                        "offense": 5005
                    },
                    "styles": [
                        {
                            "description": "primaryStyle",
                            "selections": [
                                {
                                    "perk": 8005,
                                    "var1": 2760,
                                    "var2": 1807,
                                    "var3": 953
                                },
                                {
                                    "perk": 9111,
                                    "var1": 1700,
                                    "var2": 460,
                                    "var3": 0
                                },
                                {
                                    "perk": 9104,
                                    "var1": 13,
                                    "var2": 10,
                                    "var3": 0
                                },
                                {
                                    "perk": 8014,
                                    "var1": 927,
                                    "var2": 0,
                                    "var3": 0
                                }
                            ],
                            "style": 8000
                        },
                        {
                            "description": "subStyle",
                            "selections": [
                                {
                                    "perk": 8275,
                                    "var1": 12,
                                    "var2": 0,
                                    "var3": 0
                                },
                                {
                                    "perk": 8234,
                                    "var1": 11069,
                                    "var2": 0,
                                    "var3": 0
                                }
                            ],
                            "style": 8200
                        }
                    ]
                },
                "physicalDamageDealt": 175540,
                "physicalDamageDealtToChampions": 32626,
                "physicalDamageTaken": 22220,
                "profileIcon": 4782,
                "puuid": "fyuLWfD6mhU-YkyofQnIq8b35lm1pH6ED6dH5eG-iZw2CMhoADTS14X-klLlGHO8A1hWaNxkNi6F8A",
                "quadraKills": 1,
                "riotIdName": "",
                "riotIdTagline": "",
                "role": "SOLO",
                "sightWardsBoughtInGame": 0,
                "spell1Casts": 163,
                "spell2Casts": 0,
                "spell3Casts": 8,
                "spell4Casts": 13,
                "summoner1Casts": 7,
                "summoner1Id": 6,
                "summoner2Casts": 5,
                "summoner2Id": 4,
                "summonerId": "zx9ONlyAT9rAKIisYiCnP4jnRQfBvcjr24wLm8kLpJWSIbg",
                "summonerLevel": 442,
                "summonerName": "Fuxxing JungIe",
                "teamEarlySurrendered": false,
                "teamId": 200,
                "teamPosition": "TOP",
                "timeCCingOthers": 12,
                "timePlayed": 1723,
                "totalDamageDealt": 207649,
                "totalDamageDealtToChampions": 42683,
                "totalDamageShieldedOnTeammates": 0,
                "totalDamageTaken": 27374,
                "totalHeal": 3771,
                "totalHealsOnTeammates": 0,
                "totalMinionsKilled": 207,
                "totalTimeCCDealt": 88,
                "totalTimeSpentDead": 207,
                "totalUnitsHealed": 1,
                "tripleKills": 1,
                "trueDamageDealt": 31315,
                "trueDamageDealtToChampions": 9675,
                "trueDamageTaken": 152,
                "turretKills": 4,
                "turretTakedowns": 5,
                "turretsLost": 1,
                "unrealKills": 0,
                "visionScore": 26,
                "visionWardsBoughtInGame": 4,
                "wardsKilled": 3,
                "wardsPlaced": 9,
                "win": true
            },
            {
                "assists": 7,
                "baronKills": 1,
                "bountyLevel": 0,
                "champExperience": 15334,
                "champLevel": 16,
                "championId": 141,
                "championName": "Kayn",
                "championTransform": 1,
                "consumablesPurchased": 4,
                "damageDealtToBuildings": 3137,
                "damageDealtToObjectives": 37103,
                "damageDealtToTurrets": 3137,
                "damageSelfMitigated": 28705,
                "deaths": 3,
                "detectorWardsPlaced": 3,
                "doubleKills": 3,
                "dragonKills": 3,
                "firstBloodAssist": false,
                "firstBloodKill": false,
                "firstTowerAssist": false,
                "firstTowerKill": false,
                "gameEndedInEarlySurrender": false,
                "gameEndedInSurrender": false,
                "goldEarned": 13997,
                "goldSpent": 13125,
                "individualPosition": "JUNGLE",
                "inhibitorKills": 0,
                "inhibitorTakedowns": 3,
                "inhibitorsLost": 0,
                "item0": 6630,
                "item1": 3071,
                "item2": 3082,
                "item3": 3074,
                "item4": 3024,
                "item5": 3158,
                "item6": 3364,
                "itemsPurchased": 24,
                "killingSprees": 2,
                "kills": 16,
                "lane": "JUNGLE",
                "largestCriticalStrike": 0,
                "largestKillingSpree": 12,
                "largestMultiKill": 3,
                "longestTimeSpentLiving": 942,
                "magicDamageDealt": 5494,
                "magicDamageDealtToChampions": 50,
                "magicDamageTaken": 10988,
                "neutralMinionsKilled": 121,
                "nexusKills": 0,
                "nexusLost": 0,
                "nexusTakedowns": 0,
                "objectivesStolen": 0,
                "objectivesStolenAssists": 0,
                "participantId": 7,
                "pentaKills": 0,
                "perks": {
                    "statPerks": {
                        "defense": 5002,
                        "flex": 5008,
                        "offense": 5008
                    },
                    "styles": [
                        {
                            "description": "primaryStyle",
                            "selections": [
                                {
                                    "perk": 8010,
                                    "var1": 830,
                                    "var2": 0,
                                    "var3": 0
                                },
                                {
                                    "perk": 9111,
                                    "var1": 2262,
                                    "var2": 460,
                                    "var3": 0
                                },
                                {
                                    "perk": 9105,
                                    "var1": 10,
                                    "var2": 50,
                                    "var3": 0
                                },
                                {
                                    "perk": 8299,
                                    "var1": 1201,
                                    "var2": 0,
                                    "var3": 0
                                }
                            ],
                            "style": 8000
                        },
                        {
                            "description": "subStyle",
                            "selections": [
                                {
                                    "perk": 8143,
                                    "var1": 806,
                                    "var2": 0,
                                    "var3": 0
                                },
                                {
                                    "perk": 8135,
                                    "var1": 3589,
                                    "var2": 5,
                                    "var3": 0
                                }
                            ],
                            "style": 8100
                        }
                    ]
                },
                "physicalDamageDealt": 147611,
                "physicalDamageDealtToChampions": 27093,
                "physicalDamageTaken": 30895,
                "profileIcon": 29,
                "puuid": "6RDwd3gpnYlJY_wT3qHBNhX0wh4x3RLcW8xlCkIkZVTnlVZ1zXjACOaw4MGo2yPpZTF-vBuhGcLK0g",
                "quadraKills": 0,
                "riotIdName": "",
                "riotIdTagline": "",
                "role": "NONE",
                "sightWardsBoughtInGame": 0,
                "spell1Casts": 145,
                "spell2Casts": 56,
                "spell3Casts": 22,
                "spell4Casts": 10,
                "summoner1Casts": 18,
                "summoner1Id": 11,
                "summoner2Casts": 2,
                "summoner2Id": 4,
                "summonerId": "YHSxl_5qKDMi88vQDCYF6VSSpSHWWgap8uJthem_ws2PVDc",
                "summonerLevel": 102,
                "summonerName": "Ah 내눈",
                "teamEarlySurrendered": false,
                "teamId": 200,
                "teamPosition": "JUNGLE",
                "timeCCingOthers": 24,
                "timePlayed": 1723,
                "totalDamageDealt": 169390,
                "totalDamageDealtToChampions": 28185,
                "totalDamageShieldedOnTeammates": 0,
                "totalDamageTaken": 43850,
                "totalHeal": 20078,
                "totalHealsOnTeammates": 0,
                "totalMinionsKilled": 30,
                "totalTimeCCDealt": 275,
                "totalTimeSpentDead": 72,
                "totalUnitsHealed": 1,
                "tripleKills": 1,
                "trueDamageDealt": 16285,
                "trueDamageDealtToChampions": 1042,
                "trueDamageTaken": 1966,
                "turretKills": 3,
                "turretTakedowns": 5,
                "turretsLost": 1,
                "unrealKills": 0,
                "visionScore": 23,
                "visionWardsBoughtInGame": 4,
                "wardsKilled": 1,
                "wardsPlaced": 4,
                "win": true
            },
            {
                "assists": 8,
                "baronKills": 0,
                "bountyLevel": 0,
                "champExperience": 14749,
                "champLevel": 16,
                "championId": 517,
                "championName": "Sylas",
                "championTransform": 0,
                "consumablesPurchased": 5,
                "damageDealtToBuildings": 1974,
                "damageDealtToObjectives": 8372,
                "damageDealtToTurrets": 1974,
                "damageSelfMitigated": 15440,
                "deaths": 5,
                "detectorWardsPlaced": 5,
                "doubleKills": 0,
                "dragonKills": 0,
                "firstBloodAssist": false,
                "firstBloodKill": false,
                "firstTowerAssist": false,
                "firstTowerKill": false,
                "gameEndedInEarlySurrender": false,
                "gameEndedInSurrender": false,
                "goldEarned": 9889,
                "goldSpent": 9175,
                "individualPosition": "MIDDLE",
                "inhibitorKills": 1,
                "inhibitorTakedowns": 1,
                "inhibitorsLost": 0,
                "item0": 4629,
                "item1": 0,
                "item2": 6656,
                "item3": 3191,
                "item4": 0,
                "item5": 3111,
                "item6": 3364,
                "itemsPurchased": 21,
                "killingSprees": 1,
                "kills": 3,
                "lane": "MIDDLE",
                "largestCriticalStrike": 0,
                "largestKillingSpree": 2,
                "largestMultiKill": 1,
                "longestTimeSpentLiving": 527,
                "magicDamageDealt": 104308,
                "magicDamageDealtToChampions": 13559,
                "magicDamageTaken": 10333,
                "neutralMinionsKilled": 22,
                "nexusKills": 0,
                "nexusLost": 0,
                "nexusTakedowns": 0,
                "objectivesStolen": 0,
                "objectivesStolenAssists": 0,
                "participantId": 8,
                "pentaKills": 0,
                "perks": {
                    "statPerks": {
                        "defense": 5002,
                        "flex": 5008,
                        "offense": 5008
                    },
                    "styles": [
                        {
                            "description": "primaryStyle",
                            "selections": [
                                {
                                    "perk": 8010,
                                    "var1": 213,
                                    "var2": 0,
                                    "var3": 0
                                },
                                {
                                    "perk": 8009,
                                    "var1": 2848,
                                    "var2": 0,
                                    "var3": 0
                                },
                                {
                                    "perk": 9105,
                                    "var1": 19,
                                    "var2": 0,
                                    "var3": 0
                                },
                                {
                                    "perk": 8299,
                                    "var1": 595,
                                    "var2": 0,
                                    "var3": 0
                                }
                            ],
                            "style": 8000
                        },
                        {
                            "description": "subStyle",
                            "selections": [
                                {
                                    "perk": 8345,
                                    "var1": 3,
                                    "var2": 0,
                                    "var3": 0
                                },
                                {
                                    "perk": 8352,
                                    "var1": 230,
                                    "var2": 1209,
                                    "var3": 717
                                }
                            ],
                            "style": 8300
                        }
                    ]
                },
                "physicalDamageDealt": 11677,
                "physicalDamageDealtToChampions": 2659,
                "physicalDamageTaken": 14979,
                "profileIcon": 3810,
                "puuid": "nhrRyvO26pQB8ruZrvlp0JU5qW540H_diUDW_jFdPCqmquRjRncp6J1k1B1WAm-EtbM_UrdShkdUWw",
                "quadraKills": 0,
                "riotIdName": "",
                "riotIdTagline": "",
                "role": "SOLO",
                "sightWardsBoughtInGame": 0,
                "spell1Casts": 105,
                "spell2Casts": 69,
                "spell3Casts": 125,
                "spell4Casts": 22,
                "summoner1Casts": 4,
                "summoner1Id": 12,
                "summoner2Casts": 3,
                "summoner2Id": 4,
                "summonerId": "WWr64RGDAcvkI-TPsA7AAIcnLJL_leAlcC8-BXZgbw-HBw",
                "summonerLevel": 168,
                "summonerName": "탑으로솔랭전사",
                "teamEarlySurrendered": false,
                "teamId": 200,
                "teamPosition": "MIDDLE",
                "timeCCingOthers": 29,
                "timePlayed": 1723,
                "totalDamageDealt": 116447,
                "totalDamageDealtToChampions": 16218,
                "totalDamageShieldedOnTeammates": 0,
                "totalDamageTaken": 26040,
                "totalHeal": 7436,
                "totalHealsOnTeammates": 0,
                "totalMinionsKilled": 136,
                "totalTimeCCDealt": 472,
                "totalTimeSpentDead": 140,
                "totalUnitsHealed": 1,
                "tripleKills": 0,
                "trueDamageDealt": 462,
                "trueDamageDealtToChampions": 0,
                "trueDamageTaken": 728,
                "turretKills": 1,
                "turretTakedowns": 2,
                "turretsLost": 1,
                "unrealKills": 0,
                "visionScore": 26,
                "visionWardsBoughtInGame": 5,
                "wardsKilled": 1,
                "wardsPlaced": 12,
                "win": true
            },
            {
                "assists": 7,
                "baronKills": 0,
                "bountyLevel": 0,
                "champExperience": 10707,
                "champLevel": 13,
                "championId": 145,
                "championName": "Kaisa",
                "championTransform": 0,
                "consumablesPurchased": 5,
                "damageDealtToBuildings": 4631,
                "damageDealtToObjectives": 4631,
                "damageDealtToTurrets": 4631,
                "damageSelfMitigated": 13507,
                "deaths": 10,
                "detectorWardsPlaced": 2,
                "doubleKills": 0,
                "dragonKills": 0,
                "firstBloodAssist": false,
                "firstBloodKill": false,
                "firstTowerAssist": false,
                "firstTowerKill": false,
                "gameEndedInEarlySurrender": false,
                "gameEndedInSurrender": false,
                "goldEarned": 12051,
                "goldSpent": 11325,
                "individualPosition": "BOTTOM",
                "inhibitorKills": 1,
                "inhibitorTakedowns": 2,
                "inhibitorsLost": 0,
                "item0": 3006,
                "item1": 6671,
                "item2": 3094,
                "item3": 1055,
                "item4": 6676,
                "item5": 1037,
                "item6": 3340,
                "itemsPurchased": 25,
                "killingSprees": 2,
                "kills": 8,
                "lane": "BOTTOM",
                "largestCriticalStrike": 416,
                "largestKillingSpree": 2,
                "largestMultiKill": 1,
                "longestTimeSpentLiving": 404,
                "magicDamageDealt": 11149,
                "magicDamageDealtToChampions": 6649,
                "magicDamageTaken": 5718,
                "neutralMinionsKilled": 8,
                "nexusKills": 0,
                "nexusLost": 0,
                "nexusTakedowns": 0,
                "objectivesStolen": 0,
                "objectivesStolenAssists": 0,
                "participantId": 9,
                "pentaKills": 0,
                "perks": {
                    "statPerks": {
                        "defense": 5002,
                        "flex": 5008,
                        "offense": 5005
                    },
                    "styles": [
                        {
                            "description": "primaryStyle",
                            "selections": [
                                {
                                    "perk": 9923,
                                    "var1": 50,
                                    "var2": 75,
                                    "var3": 0
                                },
                                {
                                    "perk": 8139,
                                    "var1": 898,
                                    "var2": 0,
                                    "var3": 0
                                },
                                {
                                    "perk": 8138,
                                    "var1": 18,
                                    "var2": 0,
                                    "var3": 0
                                },
                                {
                                    "perk": 8135,
                                    "var1": 2041,
                                    "var2": 4,
                                    "var3": 0
                                }
                            ],
                            "style": 8100
                        },
                        {
                            "description": "subStyle",
                            "selections": [
                                {
                                    "perk": 8304,
                                    "var1": 8,
                                    "var2": 1,
                                    "var3": 5
                                },
                                {
                                    "perk": 8345,
                                    "var1": 3,
                                    "var2": 0,
                                    "var3": 0
                                }
                            ],
                            "style": 8300
                        }
                    ]
                },
                "physicalDamageDealt": 103122,
                "physicalDamageDealtToChampions": 13827,
                "physicalDamageTaken": 17680,
                "profileIcon": 6,
                "puuid": "S0u2kZkfMqtiXGKZHZNwjv4937xWG99SD3P04AjGUBjuqI5uLdU4G2Po4de-bkHjs79xURXwnI7I3Q",
                "quadraKills": 0,
                "riotIdName": "",
                "riotIdTagline": "",
                "role": "CARRY",
                "sightWardsBoughtInGame": 0,
                "spell1Casts": 49,
                "spell2Casts": 27,
                "spell3Casts": 41,
                "spell4Casts": 8,
                "summoner1Casts": 4,
                "summoner1Id": 7,
                "summoner2Casts": 4,
                "summoner2Id": 4,
                "summonerId": "zbslc1dsJgdo6TJLo8ZUCn5IWAmRZ3tvpoJqUpOHzP2OpaM",
                "summonerLevel": 340,
                "summonerName": "vmxnz",
                "teamEarlySurrendered": false,
                "teamId": 200,
                "teamPosition": "BOTTOM",
                "timeCCingOthers": 0,
                "timePlayed": 1723,
                "totalDamageDealt": 114495,
                "totalDamageDealtToChampions": 20671,
                "totalDamageShieldedOnTeammates": 0,
                "totalDamageTaken": 24231,
                "totalHeal": 2117,
                "totalHealsOnTeammates": 690,
                "totalMinionsKilled": 165,
                "totalTimeCCDealt": 10,
                "totalTimeSpentDead": 339,
                "totalUnitsHealed": 3,
                "tripleKills": 0,
                "trueDamageDealt": 222,
                "trueDamageDealtToChampions": 194,
                "trueDamageTaken": 832,
                "turretKills": 1,
                "turretTakedowns": 3,
                "turretsLost": 1,
                "unrealKills": 0,
                "visionScore": 23,
                "visionWardsBoughtInGame": 2,
                "wardsKilled": 5,
                "wardsPlaced": 6,
                "win": true
            },
            {
                "assists": 19,
                "baronKills": 0,
                "bountyLevel": 0,
                "champExperience": 12428,
                "champLevel": 14,
                "championId": 117,
                "championName": "Lulu",
                "championTransform": 0,
                "consumablesPurchased": 7,
                "damageDealtToBuildings": 1634,
                "damageDealtToObjectives": 3338,
                "damageDealtToTurrets": 1634,
                "damageSelfMitigated": 7818,
                "deaths": 6,
                "detectorWardsPlaced": 4,
                "doubleKills": 0,
                "dragonKills": 0,
                "firstBloodAssist": false,
                "firstBloodKill": false,
                "firstTowerAssist": false,
                "firstTowerKill": false,
                "gameEndedInEarlySurrender": false,
                "gameEndedInSurrender": false,
                "goldEarned": 10519,
                "goldSpent": 9025,
                "individualPosition": "UTILITY",
                "inhibitorKills": 1,
                "inhibitorTakedowns": 3,
                "inhibitorsLost": 0,
                "item0": 3853,
                "item1": 3222,
                "item2": 3504,
                "item3": 3009,
                "item4": 6617,
                "item5": 2055,
                "item6": 3364,
                "itemsPurchased": 21,
                "killingSprees": 2,
                "kills": 6,
                "lane": "BOTTOM",
                "largestCriticalStrike": 0,
                "largestKillingSpree": 2,
                "largestMultiKill": 1,
                "longestTimeSpentLiving": 497,
                "magicDamageDealt": 18928,
                "magicDamageDealtToChampions": 7310,
                "magicDamageTaken": 4062,
                "neutralMinionsKilled": 0,
                "nexusKills": 1,
                "nexusLost": 0,
                "nexusTakedowns": 1,
                "objectivesStolen": 0,
                "objectivesStolenAssists": 0,
                "participantId": 10,
                "pentaKills": 0,
                "perks": {
                    "statPerks": {
                        "defense": 5002,
                        "flex": 5008,
                        "offense": 5008
                    },
                    "styles": [
                        {
                            "description": "primaryStyle",
                            "selections": [
                                {
                                    "perk": 8214,
                                    "var1": 1038,
                                    "var2": 1070,
                                    "var3": 0
                                },
                                {
                                    "perk": 8226,
                                    "var1": 250,
                                    "var2": 380,
                                    "var3": 0
                                },
                                {
                                    "perk": 8233,
                                    "var1": 17,
                                    "var2": 10,
                                    "var3": 0
                                },
                                {
                                    "perk": 8237,
                                    "var1": 444,
                                    "var2": 0,
                                    "var3": 0
                                }
                            ],
                            "style": 8200
                        },
                        {
                            "description": "subStyle",
                            "selections": [
                                {
                                    "perk": 8313,
                                    "var1": 0,
                                    "var2": 0,
                                    "var3": 0
                                },
                                {
                                    "perk": 8345,
                                    "var1": 3,
                                    "var2": 0,
                                    "var3": 0
                                }
                            ],
                            "style": 8300
                        }
                    ]
                },
                "physicalDamageDealt": 2741,
                "physicalDamageDealtToChampions": 1618,
                "physicalDamageTaken": 9644,
                "profileIcon": 4568,
                "puuid": "5K7-MVC9dFEiJ5cAYyf198ZWnnk0Uz4dPNdHdFFZV9jhvLLgFYP9UtIoZt-MsSqNCI32v70W2VPiag",
                "quadraKills": 0,
                "riotIdName": "",
                "riotIdTagline": "",
                "role": "SUPPORT",
                "sightWardsBoughtInGame": 0,
                "spell1Casts": 70,
                "spell2Casts": 55,
                "spell3Casts": 73,
                "spell4Casts": 7,
                "summoner1Casts": 7,
                "summoner1Id": 14,
                "summoner2Casts": 3,
                "summoner2Id": 4,
                "summonerId": "Ccq3iPS_Q4s9yVX7zQNcael5gSE0DtHY0aZk-zy9dFiaY2Q",
                "summonerLevel": 93,
                "summonerName": "휴지가급해요",
                "teamEarlySurrendered": false,
                "teamId": 200,
                "teamPosition": "UTILITY",
                "timeCCingOthers": 44,
                "timePlayed": 1723,
                "totalDamageDealt": 22615,
                "totalDamageDealtToChampions": 9874,
                "totalDamageShieldedOnTeammates": 6973,
                "totalDamageTaken": 14013,
                "totalHeal": 6537,
                "totalHealsOnTeammates": 5197,
                "totalMinionsKilled": 13,
                "totalTimeCCDealt": 347,
                "totalTimeSpentDead": 158,
                "totalUnitsHealed": 5,
                "tripleKills": 0,
                "trueDamageDealt": 944,
                "trueDamageDealtToChampions": 944,
                "trueDamageTaken": 306,
                "turretKills": 1,
                "turretTakedowns": 7,
                "turretsLost": 1,
                "unrealKills": 0,
                "visionScore": 64,
                "visionWardsBoughtInGame": 5,
                "wardsKilled": 9,
                "wardsPlaced": 23,
                "win": true
            }
        ],
        "platformId": "KR",
        "queueId": 420,
        "teams": [
            {
                "bans": [
                    {
                        "championId": 17,
                        "pickTurn": 1
                    },
                    {
                        "championId": 238,
                        "pickTurn": 2
                    },
                    {
                        "championId": 234,
                        "pickTurn": 3
                    },
                    {
                        "championId": 89,
                        "pickTurn": 4
                    },
                    {
                        "championId": 55,
                        "pickTurn": 5
                    }
                ],
                "objectives": {
                    "baron": {
                        "first": false,
                        "kills": 0
                    },
                    "champion": {
                        "first": false,
                        "kills": 30
                    },
                    "dragon": {
                        "first": true,
                        "kills": 1
                    },
                    "inhibitor": {
                        "first": false,
                        "kills": 0
                    },
                    "riftHerald": {
                        "first": false,
                        "kills": 0
                    },
                    "tower": {
                        "first": false,
                        "kills": 1
                    }
                },
                "teamId": 100,
                "win": false
            },
            {
                "bans": [
                    {
                        "championId": 412,
                        "pickTurn": 6
                    },
                    {
                        "championId": 76,
                        "pickTurn": 7
                    },
                    {
                        "championId": 89,
                        "pickTurn": 8
                    },
                    {
                        "championId": 7,
                        "pickTurn": 9
                    },
                    {
                        "championId": 115,
                        "pickTurn": 10
                    }
                ],
                "objectives": {
                    "baron": {
                        "first": true,
                        "kills": 1
                    },
                    "champion": {
                        "first": true,
                        "kills": 53
                    },
                    "dragon": {
                        "first": false,
                        "kills": 3
                    },
                    "inhibitor": {
                        "first": true,
                        "kills": 3
                    },
                    "riftHerald": {
                        "first": true,
                        "kills": 1
                    },
                    "tower": {
                        "first": true,
                        "kills": 10
                    }
                },
                "teamId": 200,
                "win": true
            }
        ],
        "tournamentCode": ""
    }
}